XCurveLearn/__init__.py
XCurveLearn/AUROC/__init__.py
XCurveLearn/AUROC/dataloaders/__init__.py
XCurveLearn/AUROC/dataloaders/base_dataset.py
XCurveLearn/AUROC/dataloaders/custom_transforms.py
XCurveLearn/AUROC/dataloaders/dataset.py
XCurveLearn/AUROC/dataloaders/sampler.py
XCurveLearn/AUROC/dataloaders/utils.py
XCurveLearn/AUROC/losses/AUROCLoss.py
XCurveLearn/AUROC/losses/PAUROCLoss.py
XCurveLearn/AUROC/losses/__init__.py
XCurveLearn/AUROC/metrics/AUROC.py
XCurveLearn/AUROC/metrics/__init__.py
XCurveLearn/AUROC/metrics/partial_AUROC.py
XCurveLearn/AUROC/models/__init__.py
XCurveLearn/AUROC/models/densenet.py
XCurveLearn/AUROC/models/load.py
XCurveLearn/AUROC/models/mlp.py
XCurveLearn/AUROC/models/resnet.py
XCurveLearn/AUROC/models/resnet_s.py
XCurveLearn/AUROC/optimizer/__init__.py
XCurveLearn/AUROC/optimizer/minmax_opt.py
XCurveLearn/AUROC/uni_test/__init__.py
XCurveLearn/AUROC/uni_test/test_dataloaders.py
XCurveLearn/AUROC/uni_test/test_losses.py
XCurveLearn/AUROC/uni_test/test_metrics.py
XCurveLearn/AUROC/uni_test/test_models.py
XCurveOpt/__init__.py
XCurveOpt/AUROC/__init__.py
XCurveOpt/AUROC/dataloaders/__init__.py
XCurveOpt/AUROC/dataloaders/base_dataset.py
XCurveOpt/AUROC/dataloaders/custom_transforms.py
XCurveOpt/AUROC/dataloaders/dataset.py
XCurveOpt/AUROC/dataloaders/sampler.py
XCurveOpt/AUROC/dataloaders/utils.py
XCurveOpt/AUROC/losses/AUROCLoss.py
XCurveOpt/AUROC/losses/PAUROCLoss.py
XCurveOpt/AUROC/losses/__init__.py
XCurveOpt/AUROC/metrics/AUROC.py
XCurveOpt/AUROC/metrics/__init__.py
XCurveOpt/AUROC/metrics/partial_AUROC.py
XCurveOpt/AUROC/models/__init__.py
XCurveOpt/AUROC/models/densenet.py
XCurveOpt/AUROC/models/load.py
XCurveOpt/AUROC/models/mlp.py
XCurveOpt/AUROC/models/resnet.py
XCurveOpt/AUROC/models/resnet_s.py
XCurveOpt/AUROC/optimizer/__init__.py
XCurveOpt/AUROC/optimizer/minmax_opt.py
XCurveOpt/AUROC/uni_test/__init__.py
XCurveOpt/AUROC/uni_test/test_dataloaders.py
XCurveOpt/AUROC/uni_test/test_losses.py
XCurveLearn-0.0.5.dist-info/METADATA
XCurveLearn-0.0.5.dist-info/WHEEL
XCurveLearn-0.0.5.dist-info/top_level.txt
XCurveLearn-0.0.5.dist-info/RECORD
