Metadata-Version: 2.1
Name: XCurveLearn
Version: 0.0.5
Summary: machine learning package
Home-page: https://gitee.com/Statusrank/xcurve-opt
Author: qqgroup
Author-email: 
License: UNKNOWN
Platform: UNKNOWN
Classifier: Programming Language :: Python :: 3
Classifier: License :: OSI Approved :: MIT License
Classifier: Operating System :: OS Independent
Requires-Python: >=3.7
Requires-Dist: easydict (>=1.9)
Requires-Dist: imblearn (>=0.0)
Requires-Dist: lmdb (>=1.3.0)
Requires-Dist: numpy (>=1.21.2)
Requires-Dist: opencv-python (>=4.5.5.62)
Requires-Dist: pandas (>=1.1.0)
Requires-Dist: Pillow (>=9.1.1)
Requires-Dist: pytest (>=7.1.2)
Requires-Dist: scikit-learn (>=1.1.1)
Requires-Dist: scipy (>=1.7.1)
Requires-Dist: scikit-image (>=0.18.0)
Requires-Dist: torch (>=1.11.0)
Requires-Dist: torchvision (>=0.12.0)
Requires-Dist: tqdm (>=4.62.2)
